<?xml version="1.0" encoding="utf-8"?>
<!DOCTYPE list SYSTEM "spawn.dtd">
<list>
	<spawn count="1" respawn="60" respawn_random="0" period_of_day="none">
		<point x="-149541" y="254164" z="-184" h="0"/>
		<npc id="32629"/><!--Wharf Patrol-->
	</spawn>
	<spawn count="1" respawn="60" respawn_random="0" period_of_day="none">
		<point x="-149616" y="254152" z="-181" h="0"/>
		<npc id="32629"/><!--Wharf Patrol-->
	</spawn>
	<spawn count="1" respawn="60" respawn_random="0" period_of_day="none">
		<point x="-149649" y="255028" z="-85" h="0"/>
		<npc id="32614"/><!--Lamcedas-->
	</spawn>
	<spawn count="1" respawn="60" respawn_random="0" period_of_day="none">
		<point x="-148656" y="253841" z="-185" h="0"/>
		<npc id="32616"/><!--Mine-->
	</spawn>
	<spawn count="1" respawn="60" respawn_random="0" period_of_day="none">
		<point x="-149235" y="253680" z="-185" h="0"/>
		<npc id="32565"/><!--Felix-->
	</spawn>
	<spawn count="1" respawn="60" respawn_random="0" period_of_day="none">
		<point x="-149360" y="252936" z="-137" h="0"/>
		<npc id="32609"/><!--Flight Device-->
	</spawn>
	<spawn count="1" respawn="60" respawn_random="0" period_of_day="none">
		<point x="-148540" y="254527" z="-184" h="0"/>
		<npc id="32628"/><!--Wharf Patrol-->
	</spawn>
	<spawn count="1" respawn="60" respawn_random="0" period_of_day="none">
		<point x="-148495" y="254645" z="-184" h="0"/>
		<npc id="32628"/><!--Wharf Patrol-->
	</spawn>
	<spawn count="1" respawn="60" respawn_random="0" period_of_day="none">
		<point x="-149067" y="255028" z="-91" h="0"/>
		<npc id="32615"/><!--Ishuma-->
	</spawn>
</list>