<?xml version='1.0' encoding='utf-8'?>
<!DOCTYPE list SYSTEM "multisell.dtd">
<!--Trader Alexandria (Luxury Shop) Armor-->
<list>
	<config no_tax="true"/>
	<item>
		<production id="357" count="1"/>	<!--Кираса Зубея-->
		<ingredient id="57" count="1596000"/>	<!--Адена-->
	</item>
	<item>
		<production id="383" count="1"/>	<!--Набедренники Зубея-->
		<ingredient id="57" count="997700"/>	<!--Адена-->
	</item>
	<item>
		<production id="503" count="1"/>	<!--Шлем Зубея-->
		<ingredient id="57" count="598600"/>	<!--Адена-->
	</item>
	<item>
		<production id="554" count="1"/>	<!--Запечатанные Сапоги Зубея-->
		<ingredient id="57" count="399100"/>	<!--Адена-->
	</item>
	<item>
		<production id="600" count="1"/>	<!--Запечатанные Сапоги Авадона-->
		<ingredient id="57" count="399100"/>	<!--Адена-->
	</item>
	<item>
		<production id="612" count="1"/>	<!--Запечатанные Рукавицы Зубея-->
		<ingredient id="57" count="399100"/>	<!--Адена-->
	</item>
	<item>
		<production id="633" count="1"/>	<!--Щит Зубея-->
		<ingredient id="57" count="419000"/>	<!--Адена-->
	</item>
	<item>
		<production id="673" count="1"/>	<!--Щит Авадона-->
		<ingredient id="57" count="419000"/>	<!--Адена-->
	</item>
	<item>
		<production id="2376" count="1"/>	<!--Кираса Авадона-->
		<ingredient id="57" count="1596000"/>	<!--Адена-->
	</item>
	<item>
		<production id="2379" count="1"/>	<!--Набедренники Авадона-->
		<ingredient id="57" count="997700"/>	<!--Адена-->
	</item>
	<item>
		<production id="2384" count="1"/>	<!--Кожаная Рубаха Зубея-->
		<ingredient id="57" count="1197000"/>	<!--Адена-->
	</item>
	<item>
		<production id="2388" count="1"/>	<!--Кожаные Набедренники Зубея-->
		<ingredient id="57" count="748300"/>	<!--Адена-->
	</item>
	<item>
		<production id="2390" count="1"/>	<!--Кожаный Доспех Авадона-->
		<ingredient id="57" count="1946000"/>	<!--Адена-->
	</item>
	<item>
		<production id="2397" count="1"/>	<!--Туника Зубея-->
		<ingredient id="57" count="1197000"/>	<!--Адена-->
	</item>
	<item>
		<production id="2402" count="1"/>	<!--Штаны Зубея-->
		<ingredient id="57" count="748300"/>	<!--Адена-->
	</item>
	<item>
		<production id="2406" count="1"/>	<!--Мантия Авадона-->
		<ingredient id="57" count="1946000"/>	<!--Адена-->
	</item>
	<item>
		<production id="2415" count="1"/>	<!--Диадема Авадона-->
		<ingredient id="57" count="598600"/>	<!--Адена-->
	</item>
	<item>
		<production id="2464" count="1"/>	<!--Запечатанные Перчатки Авадона-->
		<ingredient id="57" count="399100"/>	<!--Адена-->
	</item>
	<item>
		<production id="365" count="1"/>	<!--Кираса Кристалла Тьмы-->
		<ingredient id="57" count="3562000"/>	<!--Адена-->
	</item>
	<item>
		<production id="388" count="1"/>	<!--Набедренники Кристалла Тьмы-->
		<ingredient id="57" count="2226000"/>	<!--Адена-->
	</item>
	<item>
		<production id="512" count="1"/>	<!--Шлем Кристалла Тьмы-->
		<ingredient id="57" count="1336000"/>	<!--Адена-->
	</item>
	<item>
		<production id="641" count="1"/>	<!--Щит Кристалла Тьмы-->
		<ingredient id="57" count="935000"/>	<!--Адена-->
	</item>
	<item>
		<production id="2385" count="1"/>	<!--Кожаный Доспех Кристалла Тьмы-->
		<ingredient id="57" count="2671000"/>	<!--Адена-->
	</item>
	<item>
		<production id="2389" count="1"/>	<!--Поножи Кристалла Тьмы-->
		<ingredient id="57" count="1670000"/>	<!--Адена-->
	</item>
	<item>
		<production id="2407" count="1"/>	<!--Мантия Кристалла Тьмы-->
		<ingredient id="57" count="4341000"/>	<!--Адена-->
	</item>
	<item>
		<production id="2382" count="1"/>	<!--Латный Доспех Таллума-->
		<ingredient id="57" count="5788000"/>	<!--Адена-->
	</item>
	<item>
		<production id="547" count="1"/>	<!--Шлем Таллума-->
		<ingredient id="57" count="1336000"/>	<!--Адена-->
	</item>
	<item>
		<production id="2393" count="1"/>	<!--Кожаный Доспех Таллума-->
		<ingredient id="57" count="4341000"/>	<!--Адена-->
	</item>
	<item>
		<production id="2400" count="1"/>	<!--Туника Таллума-->
		<ingredient id="57" count="2671000"/>	<!--Адена-->
	</item>
	<item>
		<production id="2405" count="1"/>	<!--Штаны Таллума-->
		<ingredient id="57" count="1670000"/>	<!--Адена-->
	</item>
	<item>
		<production id="5290" count="1"/>	<!--Запечатанные Перчатки Кристалла Тьмы-->
		<ingredient id="57" count="890000"/>	<!--Адена-->
	</item>
	<item>
		<production id="5295" count="1"/>	<!--Запечатанные Перчатки Таллума-->
		<ingredient id="57" count="890000"/>	<!--Адена-->
	</item>
	<item>
		<production id="5291" count="1"/>	<!--Запечатанные Сапоги Кристалла Тьмы-->
		<ingredient id="57" count="890000"/>	<!--Адена-->
	</item>
	<item>
		<production id="5296" count="1"/>	<!--Запечатанные Сапоги Таллума-->
		<ingredient id="57" count="890000"/>	<!--Адена-->
	</item>
	<item>
		<production id="6323" count="1"/>	<!--Запечатанное Ожерелье Феникса-->
		<ingredient id="57" count="1340000"/>	<!--Адена-->
	</item>
	<item>
		<production id="6324" count="1"/>	<!--Запечатанная Серьга Феникса-->
		<ingredient id="57" count="1005000"/>	<!--Адена-->
	</item>
	<item>
		<production id="6325" count="1"/>	<!--Запечатанное Кольцо Феникса-->
		<ingredient id="57" count="670000"/>	<!--Адена-->
	</item>
	<item>
		<production id="6326" count="1"/>	<!--Запечатанное Ожерелье Величия-->
		<ingredient id="57" count="1998000"/>	<!--Адена-->
	</item>
	<item>
		<production id="6327" count="1"/>	<!--Запечатанная Серьга Величия-->
		<ingredient id="57" count="1498000"/>	<!--Адена-->
	</item>
	<item>
		<production id="6328" count="1"/>	<!--Запечатанное Кольцо Величия-->
		<ingredient id="57" count="999000"/>	<!--Адена-->
	</item>
	<item>
		<production id="918" count="1"/>	<!--Адамантитовое Ожерелье-->
		<ingredient id="57" count="621200"/>	<!--Адена-->
	</item>
	<item>
		<production id="926" count="1"/>	<!--Черное Ожерелье-->
		<ingredient id="57" count="948000"/>	<!--Адена-->
	</item>
	<item>
		<production id="856" count="1"/>	<!--Адамантитовая Серьга-->
		<ingredient id="57" count="465900"/>	<!--Адена-->
	</item>
	<item>
		<production id="864" count="1"/>	<!--Черная Серьга-->
		<ingredient id="57" count="711000"/>	<!--Адена-->
	</item>
	<item>
		<production id="887" count="1"/>	<!--Адамантитовое Кольцо-->
		<ingredient id="57" count="310600"/>	<!--Адена-->
	</item>
	<item>
		<production id="895" count="1"/>	<!--Черное Кольцо-->
		<ingredient id="57" count="474000"/>	<!--Адена-->
	</item>
</list>