<?xml version="1.0" encoding="UTF-8"?>
<!DOCTYPE list SYSTEM "spawn.dtd">
<list>
    <spawn count="1" respawn="60" respawn_random="0" period_of_day="none">
        <point x="6973" y="-108195" z="-1912" h="56802"/>
        <npc id="23352"/>	<!--Дикое Дерево Тайник-->
    </spawn>
    <spawn count="1" respawn="60" respawn_random="0" period_of_day="none">
        <point x="6292" y="-103733" z="-2536" h="25985"/>
        <npc id="23353"/>	<!--Дикий Хранитель-->
    </spawn>
    <spawn count="1" respawn="60" respawn_random="0" period_of_day="none">
        <point x="6029" y="-108195" z="-2168" h="25302"/>
        <npc id="23353"/>	<!--Дикий Хранитель-->
    </spawn>
    <spawn count="1" respawn="60" respawn_random="0" period_of_day="none">
        <point x="5793" y="-108195" z="-2248" h="9422"/>
        <npc id="23351"/>	<!--Дикое Дерево Хранитель-->
    </spawn>
    <spawn count="1" respawn="60" respawn_random="0" period_of_day="none">
        <point x="5230" y="-105113" z="-2600" h="24828"/>
        <npc id="23353"/>	<!--Дикий Хранитель-->
    </spawn>
    <spawn count="1" respawn="60" respawn_random="0" period_of_day="none">
        <point x="4522" y="-106493" z="-2704" h="30681"/>
        <npc id="23352"/>	<!--Дикое Дерево Тайник-->
    </spawn>
    <spawn count="1" respawn="60" respawn_random="0" period_of_day="none">
        <point x="4522" y="-105113" z="-2568" h="11488"/>
        <npc id="23352"/>	<!--Дикое Дерево Тайник-->
    </spawn>
    <spawn count="1" respawn="60" respawn_random="0" period_of_day="none">
        <point x="4522" y="-105803" z="-2632" h="46681"/>
        <npc id="23352"/>	<!--Дикое Дерево Тайник-->
    </spawn>
    <spawn count="1" respawn="60" respawn_random="0" period_of_day="none">
        <point x="4168" y="-103043" z="-2152" h="34772"/>
        <npc id="23352"/>	<!--Дикое Дерево Тайник-->
    </spawn>
    <spawn count="1" respawn="60" respawn_random="0" period_of_day="none">
        <point x="5584" y="-103733" z="-2456" h="15191"/>
        <npc id="23352"/>	<!--Дикое Дерево Тайник-->
    </spawn>
    <spawn count="1" respawn="60" respawn_random="0" period_of_day="none">
        <point x="3814" y="-106493" z="-2680" h="36559"/>
        <npc id="23352"/>	<!--Дикое Дерево Тайник-->
    </spawn>
    <spawn count="1" respawn="60" respawn_random="0" period_of_day="none">
        <point x="2398" y="-105803" z="-2592" h="64317"/>
        <npc id="23353"/>	<!--Дикий Хранитель-->
    </spawn>
    <spawn count="1" respawn="60" respawn_random="0" period_of_day="none">
        <point x="2752" y="-105113" z="-2512" h="29879"/>
        <npc id="23351"/>	<!--Дикое Дерево Хранитель-->
    </spawn>
    <spawn count="1" respawn="60" respawn_random="0" period_of_day="none">
        <point x="2398" y="-104423" z="-2448" h="65478"/>
        <npc id="23351"/>	<!--Дикое Дерево Хранитель-->
    </spawn>
    <spawn count="1" respawn="60" respawn_random="0" period_of_day="none">
        <point x="3460" y="-103043" z="-2128" h="30174"/>
        <npc id="23352"/>	<!--Дикое Дерево Тайник-->
    </spawn>
    <spawn count="1" respawn="60" respawn_random="0" period_of_day="none">
        <point x="3106" y="-103733" z="-2312" h="44730"/>
        <npc id="23351"/>	<!--Дикое Дерево Хранитель-->
    </spawn>
    <spawn count="1" respawn="60" respawn_random="0" period_of_day="none">
        <point x="2752" y="-103733" z="-2336" h="9994"/>
        <npc id="23351"/>	<!--Дикое Дерево Хранитель-->
    </spawn>
    <spawn count="1" respawn="60" respawn_random="0" period_of_day="none">
        <point x="2752" y="-103043" z="-2168" h="52801"/>
        <npc id="23351"/>	<!--Дикое Дерево Хранитель-->
    </spawn>
    <spawn count="1" respawn="60" respawn_random="0" period_of_day="none">
        <point x="3106" y="-102353" z="-1992" h="18704"/>
        <npc id="23353"/>	<!--Дикий Хранитель-->
    </spawn>
    <spawn count="1" respawn="60" respawn_random="0" period_of_day="none">
        <point x="5584" y="-102353" z="-2264" h="32077"/>
        <npc id="23353"/>	<!--Дикий Хранитель-->
    </spawn>
    <spawn count="1" respawn="60" respawn_random="0" period_of_day="none">
        <point x="5938" y="-100973" z="-2104" h="56670"/>
        <npc id="23352"/>	<!--Дикое Дерево Тайник-->
    </spawn>
    <spawn count="1" respawn="60" respawn_random="0" period_of_day="none">
        <point x="4168" y="-100973" z="-1848" h="40911"/>
        <npc id="23352"/>	<!--Дикое Дерево Тайник-->
    </spawn>
    <spawn count="1" respawn="60" respawn_random="0" period_of_day="none">
        <point x="5230" y="-102353" z="-2176" h="26632"/>
        <npc id="23351"/>	<!--Дикое Дерево Хранитель-->
    </spawn>
    <spawn count="1" respawn="60" respawn_random="0" period_of_day="none">
        <point x="4522" y="-100973" z="-1936" h="49033"/>
        <npc id="23351"/>	<!--Дикое Дерево Хранитель-->
    </spawn>
    <spawn count="1" respawn="60" respawn_random="0" period_of_day="none">
        <point x="1338" y="-107918" z="-2760" h="49646"/>
        <npc id="23353"/>	<!--Дикий Хранитель-->
    </spawn>
    <spawn count="1" respawn="60" respawn_random="0" period_of_day="none">
        <point x="607" y="-107728" z="-2760" h="17863"/>
        <npc id="23352"/>	<!--Дикое Дерево Тайник-->
    </spawn>
    <spawn count="1" respawn="60" respawn_random="0" period_of_day="none">
        <point x="1336" y="-107183" z="-2736" h="52247"/>
        <npc id="23351"/>	<!--Дикое Дерево Хранитель-->
    </spawn>
    <spawn count="1" respawn="60" respawn_random="0" period_of_day="none">
        <point x="1336" y="-105803" z="-2616" h="25210"/>
        <npc id="23353"/>	<!--Дикий Хранитель-->
    </spawn>
    <spawn count="1" respawn="60" respawn_random="0" period_of_day="none">
        <point x="982" y="-106493" z="-2688" h="55828"/>
        <npc id="23353"/>	<!--Дикий Хранитель-->
    </spawn>
    <spawn count="1" respawn="60" respawn_random="0" period_of_day="none">
        <point x="628" y="-105113" z="-2576" h="9512"/>
        <npc id="23353"/>	<!--Дикий Хранитель-->
    </spawn>
    <spawn count="1" respawn="60" respawn_random="0" period_of_day="none">
        <point x="1690" y="-105803" z="-2600" h="9232"/>
        <npc id="23351"/>	<!--Дикое Дерево Хранитель-->
    </spawn>
    <spawn count="1" respawn="60" respawn_random="0" period_of_day="none">
        <point x="1336" y="-105113" z="-2544" h="28709"/>
        <npc id="23351"/>	<!--Дикое Дерево Хранитель-->
    </spawn>
    <spawn count="1" respawn="60" respawn_random="0" period_of_day="none">
        <point x="628" y="-103733" z="-2424" h="64771"/>
        <npc id="23353"/>	<!--Дикий Хранитель-->
    </spawn>
    <spawn count="1" respawn="60" respawn_random="0" period_of_day="none">
        <point x="2006" y="-104395" z="-2448" h="26136"/>
        <npc id="23353"/>	<!--Дикий Хранитель-->
    </spawn>
    <spawn count="1" respawn="60" respawn_random="0" period_of_day="none">
        <point x="982" y="-103043" z="-2296" h="33254"/>
        <npc id="23352"/>	<!--Дикое Дерево Тайник-->
    </spawn>
    <spawn count="1" respawn="60" respawn_random="0" period_of_day="none">
        <point x="1365" y="-103740" z="-2392" h="62988"/>
        <npc id="23352"/>	<!--Дикое Дерево Тайник-->
    </spawn>
    <spawn count="1" respawn="60" respawn_random="0" period_of_day="none">
        <point x="2044" y="-104423" z="-2448" h="8085"/>
        <npc id="23351"/>	<!--Дикое Дерево Хранитель-->
    </spawn>
    <spawn count="1" respawn="60" respawn_random="0" period_of_day="none">
        <point x="628" y="-109943" z="-2648" h="28468"/>
        <npc id="23353"/>	<!--Дикий Хранитель-->
    </spawn>
    <spawn count="1" respawn="60" respawn_random="0" period_of_day="none">
        <point x="2044" y="-109253" z="-2512" h="43378"/>
        <npc id="23351"/>	<!--Дикое Дерево Хранитель-->
    </spawn>
    <spawn count="1" respawn="60" respawn_random="0" period_of_day="none">
        <point x="628" y="-109253" z="-2728" h="52006"/>
        <npc id="23352"/>	<!--Дикое Дерево Тайник-->
    </spawn>
    <spawn count="1" respawn="60" respawn_random="0" period_of_day="none">
        <point x="2044" y="-109253" z="-2512" h="39232"/>
        <npc id="23351"/>	<!--Дикое Дерево Хранитель-->
    </spawn>
    <spawn count="1" respawn="60" respawn_random="0" period_of_day="none">
        <point x="1690" y="-108563" z="-2696" h="25395"/>
        <npc id="23351"/>	<!--Дикое Дерево Хранитель-->
    </spawn>
    <spawn count="1" respawn="60" respawn_random="0" period_of_day="none">
        <point x="2752" y="-109253" z="-2416" h="56205"/>
        <npc id="23353"/>	<!--Дикий Хранитель-->
    </spawn>
    <spawn count="1" respawn="60" respawn_random="0" period_of_day="none">
        <point x="2398" y="-109943" z="-2368" h="6347"/>
        <npc id="23352"/>	<!--Дикое Дерево Тайник-->
    </spawn>
    <spawn count="1" respawn="60" respawn_random="0" period_of_day="none">
        <point x="5990" y="-108650" z="-2112" h="38942"/>
        <npc id="23353"/>	<!--Дикий Хранитель-->
    </spawn>
    <spawn count="1" respawn="60" respawn_random="0" period_of_day="none">
        <point x="5085" y="-110345" z="-2024" h="37917"/>
        <npc id="23353"/>	<!--Дикий Хранитель-->
    </spawn>
    <spawn count="1" respawn="60" respawn_random="0" period_of_day="none">
        <point x="5085" y="-109485" z="-2200" h="20752"/>
        <npc id="23351"/>	<!--Дикое Дерево Хранитель-->
    </spawn>
    <spawn count="1" respawn="60" respawn_random="0" period_of_day="none">
        <point x="5793" y="-109055" z="-2080" h="2853"/>
        <npc id="23352"/>	<!--Дикое Дерево Тайник-->
    </spawn>
    <spawn count="1" respawn="60" respawn_random="0" period_of_day="none">
        <point x="5793" y="-109485" z="-2016" h="53028"/>
        <npc id="23352"/>	<!--Дикое Дерево Тайник-->
    </spawn>
    <spawn count="1" respawn="60" respawn_random="0" period_of_day="none">
        <point x="5557" y="-109915" z="-2008" h="63753"/>
        <npc id="23352"/>	<!--Дикое Дерево Тайник-->
    </spawn>
    <spawn count="1" respawn="60" respawn_random="0" period_of_day="none">
        <point x="4849" y="-109915" z="-2152" h="3198"/>
        <npc id="23351"/>	<!--Дикое Дерево Хранитель-->
    </spawn>
    <spawn count="1" respawn="60" respawn_random="0" period_of_day="none">
        <point x="5557" y="-109485" z="-2064" h="42111"/>
        <npc id="23351"/>	<!--Дикое Дерево Хранитель-->
    </spawn>
    <spawn count="1" respawn="60" respawn_random="0" period_of_day="none">
        <point x="3669" y="-112495" z="-2168" h="56322"/>
        <npc id="23352"/>	<!--Дикое Дерево Тайник-->
    </spawn>
    <spawn count="1" respawn="60" respawn_random="0" period_of_day="none">
        <point x="3905" y="-112495" z="-2152" h="62424"/>
        <npc id="23352"/>	<!--Дикое Дерево Тайник-->
    </spawn>
    <spawn count="1" respawn="60" respawn_random="0" period_of_day="none">
        <point x="3905" y="-111205" z="-2096" h="31945"/>
        <npc id="23351"/>	<!--Дикое Дерево Хранитель-->
    </spawn>
    <spawn count="1" respawn="60" respawn_random="0" period_of_day="none">
        <point x="3669" y="-111635" z="-2128" h="50955"/>
        <npc id="23351"/>	<!--Дикое Дерево Хранитель-->
    </spawn>
    <spawn count="1" respawn="60" respawn_random="0" period_of_day="none">
        <point x="5557" y="-111635" z="-1864" h="5003"/>
        <npc id="23353"/>	<!--Дикий Хранитель-->
    </spawn>
    <spawn count="1" respawn="60" respawn_random="0" period_of_day="none">
        <point x="4613" y="-112495" z="-2072" h="8333"/>
        <npc id="23351"/>	<!--Дикое Дерево Хранитель-->
    </spawn>
    <spawn count="1" respawn="60" respawn_random="0" period_of_day="none">
        <point x="5321" y="-111205" z="-1936" h="21997"/>
        <npc id="23353"/>	<!--Дикий Хранитель-->
    </spawn>
    <spawn count="1" respawn="60" respawn_random="0" period_of_day="none">
        <point x="5557" y="-112065" z="-1832" h="54456"/>
        <npc id="23353"/>	<!--Дикий Хранитель-->
    </spawn>
    <spawn count="1" respawn="60" respawn_random="0" period_of_day="none">
        <point x="6029" y="-110775" z="-1792" h="46818"/>
        <npc id="23351"/>	<!--Дикое Дерево Хранитель-->
    </spawn>
    <spawn count="1" respawn="60" respawn_random="0" period_of_day="none">
        <point x="5085" y="-112495" z="-1944" h="54658"/>
        <npc id="23353"/>	<!--Дикий Хранитель-->
    </spawn>
    <spawn count="1" respawn="60" respawn_random="0" period_of_day="none">
        <point x="4141" y="-110775" z="-2096" h="56651"/>
        <npc id="23353"/>	<!--Дикий Хранитель-->
    </spawn>
    <spawn count="1" respawn="60" respawn_random="0" period_of_day="none">
        <point x="5085" y="-110775" z="-1984" h="54995"/>
        <npc id="23353"/>	<!--Дикий Хранитель-->
    </spawn>
    <spawn count="1" respawn="60" respawn_random="0" period_of_day="none">
        <point x="6029" y="-112495" z="-1752" h="42653"/>
        <npc id="23352"/>	<!--Дикое Дерево Тайник-->
    </spawn>
    <spawn count="1" respawn="60" respawn_random="0" period_of_day="none">
        <point x="5321" y="-110775" z="-1952" h="51587"/>
        <npc id="23352"/>	<!--Дикое Дерево Тайник-->
    </spawn>
    <spawn count="1" respawn="60" respawn_random="0" period_of_day="none">
        <point x="4613" y="-111635" z="-2072" h="26341"/>
        <npc id="23352"/>	<!--Дикое Дерево Тайник-->
    </spawn>
    <spawn count="1" respawn="60" respawn_random="0" period_of_day="none">
        <point x="5321" y="-110775" z="-1952" h="47526"/>
        <npc id="23351"/>	<!--Дикое Дерево Хранитель-->
    </spawn>
    <spawn count="1" respawn="60" respawn_random="0" period_of_day="none">
        <point x="4849" y="-111635" z="-2040" h="14239"/>
        <npc id="23351"/>	<!--Дикое Дерево Хранитель-->
    </spawn>
    <spawn count="1" respawn="60" respawn_random="0" period_of_day="none">
        <point x="4849" y="-113785" z="-1888" h="58170"/>
        <npc id="23353"/>	<!--Дикий Хранитель-->
    </spawn>
    <spawn count="1" respawn="60" respawn_random="0" period_of_day="none">
        <point x="4141" y="-112925" z="-2104" h="36052"/>
        <npc id="23353"/>	<!--Дикий Хранитель-->
    </spawn>
    <spawn count="1" respawn="60" respawn_random="0" period_of_day="none">
        <point x="278" y="-116446" z="-2376" h="11621"/>
        <npc id="23353"/>	<!--Дикий Хранитель-->
    </spawn>
    <spawn count="1" respawn="60" respawn_random="0" period_of_day="none">
        <point x="1587" y="-116446" z="-2352" h="38203"/>
        <npc id="23352"/>	<!--Дикое Дерево Тайник-->
    </spawn>
    <spawn count="1" respawn="60" respawn_random="0" period_of_day="none">
        <point x="1587" y="-116446" z="-2352" h="63964"/>
        <npc id="23351"/>	<!--Дикое Дерево Хранитель-->
    </spawn>
    <spawn count="1" respawn="60" respawn_random="0" period_of_day="none">
        <point x="2148" y="-116446" z="-2344" h="3238"/>
        <npc id="23353"/>	<!--Дикий Хранитель-->
    </spawn>
    <spawn count="1" respawn="60" respawn_random="0" period_of_day="none">
        <point x="2896" y="-116732" z="-2320" h="52295"/>
        <npc id="23353"/>	<!--Дикий Хранитель-->
    </spawn>
    <spawn count="1" respawn="60" respawn_random="0" period_of_day="none">
        <point x="2709" y="-116732" z="-2336" h="36072"/>
        <npc id="23353"/>	<!--Дикий Хранитель-->
    </spawn>
    <spawn count="1" respawn="60" respawn_random="0" period_of_day="none">
        <point x="2896" y="-116732" z="-2320" h="653"/>
        <npc id="23351"/>	<!--Дикое Дерево Хранитель-->
    </spawn>
    <spawn count="1" respawn="60" respawn_random="0" period_of_day="none">
        <point x="2148" y="-116446" z="-2344" h="2119"/>
        <npc id="23352"/>	<!--Дикое Дерево Тайник-->
    </spawn>
    <spawn count="1" respawn="60" respawn_random="0" period_of_day="none">
        <point x="2522" y="-116446" z="-2320" h="27925"/>
        <npc id="23351"/>	<!--Дикое Дерево Хранитель-->
    </spawn>
    <spawn count="1" respawn="60" respawn_random="0" period_of_day="none">
        <point x="6273" y="-112970" z="-1736" h="51138"/>
        <npc id="23353"/>	<!--Дикий Хранитель-->
    </spawn>
    <spawn count="1" respawn="60" respawn_random="0" period_of_day="none">
        <point x="6243" y="-113218" z="-1736" h="50732"/>
        <npc id="23353"/>	<!--Дикий Хранитель-->
    </spawn>
    <spawn count="1" respawn="60" respawn_random="0" period_of_day="none">
        <point x="6265" y="-114215" z="-1736" h="21145"/>
        <npc id="23351"/>	<!--Дикое Дерево Хранитель-->
    </spawn>
    <spawn count="1" respawn="60" respawn_random="0" period_of_day="none">
        <point x="6915" y="-111959" z="-1736" h="21608"/>
        <npc id="23352"/>	<!--Дикое Дерево Тайник-->
    </spawn>
    <spawn count="1" respawn="60" respawn_random="0" period_of_day="none">
        <point x="6452" y="-111140" z="-1736" h="3456"/>
        <npc id="23351"/>	<!--Дикое Дерево Хранитель-->
    </spawn>
    <spawn count="1" respawn="60" respawn_random="0" period_of_day="none">
        <point x="6422" y="-111384" z="-1736" h="44874"/>
        <npc id="23351"/>	<!--Дикое Дерево Хранитель-->
    </spawn>
    <spawn count="1" respawn="60" respawn_random="0" period_of_day="none">
        <point x="2148" y="-117161" z="-2448" h="29773"/>
        <npc id="23353"/>	<!--Дикий Хранитель-->
    </spawn>
    <spawn count="1" respawn="60" respawn_random="0" period_of_day="none">
        <point x="3083" y="-116875" z="-2336" h="54150"/>
        <npc id="23353"/>	<!--Дикий Хранитель-->
    </spawn>
    <spawn count="1" respawn="60" respawn_random="0" period_of_day="none">
        <point x="2148" y="-118019" z="-2632" h="17563"/>
        <npc id="23353"/>	<!--Дикий Хранитель-->
    </spawn>
    <spawn count="1" respawn="60" respawn_random="0" period_of_day="none">
        <point x="2522" y="-118448" z="-2704" h="20508"/>
        <npc id="23351"/>	<!--Дикое Дерево Хранитель-->
    </spawn>
    <spawn count="1" respawn="60" respawn_random="0" period_of_day="none">
        <point x="2896" y="-117018" z="-2376" h="61106"/>
        <npc id="23353"/>	<!--Дикий Хранитель-->
    </spawn>
    <spawn count="1" respawn="60" respawn_random="0" period_of_day="none">
        <point x="2335" y="-118591" z="-2728" h="2362"/>
        <npc id="23352"/>	<!--Дикое Дерево Тайник-->
    </spawn>
    <spawn count="1" respawn="60" respawn_random="0" period_of_day="none">
        <point x="3644" y="-117590" z="-2424" h="33030"/>
        <npc id="23352"/>	<!--Дикое Дерево Тайник-->
    </spawn>
    <spawn count="1" respawn="60" respawn_random="0" period_of_day="none">
        <point x="3083" y="-117304" z="-2400" h="48426"/>
        <npc id="23352"/>	<!--Дикое Дерево Тайник-->
    </spawn>
    <spawn count="1" respawn="60" respawn_random="0" period_of_day="none">
        <point x="2896" y="-117161" z="-2392" h="57445"/>
        <npc id="23352"/>	<!--Дикое Дерево Тайник-->
    </spawn>
    <spawn count="1" respawn="60" respawn_random="0" period_of_day="none">
        <point x="3083" y="-118305" z="-2640" h="49080"/>
        <npc id="23352"/>	<!--Дикое Дерево Тайник-->
    </spawn>
    <spawn count="1" respawn="60" respawn_random="0" period_of_day="none">
        <point x="2896" y="-117447" z="-2440" h="42732"/>
        <npc id="23351"/>	<!--Дикое Дерево Хранитель-->
    </spawn>
    <spawn count="1" respawn="60" respawn_random="0" period_of_day="none">
        <point x="3457" y="-118448" z="-2600" h="9141"/>
        <npc id="23351"/>	<!--Дикое Дерево Хранитель-->
    </spawn>
    <spawn count="1" respawn="60" respawn_random="0" period_of_day="none">
        <point x="2896" y="-116875" z="-2352" h="8002"/>
        <npc id="23351"/>	<!--Дикое Дерево Хранитель-->
    </spawn>
    <spawn count="1" respawn="60" respawn_random="0" period_of_day="none">
        <point x="6991" y="-118100" z="-1808" h="9765"/>
        <npc id="23353"/>	<!--Дикий Хранитель-->
    </spawn>
    <spawn count="1" respawn="60" respawn_random="0" period_of_day="none">
        <point x="7233" y="-118100" z="-1808" h="7480"/>
        <npc id="23352"/>	<!--Дикое Дерево Тайник-->
    </spawn>
    <spawn count="1" respawn="60" respawn_random="0" period_of_day="none">
        <point x="7475" y="-118520" z="-1824" h="13448"/>
        <npc id="23353"/>	<!--Дикий Хранитель-->
    </spawn>
    <spawn count="1" respawn="60" respawn_random="0" period_of_day="none">
        <point x="6023" y="-118940" z="-1968" h="4774"/>
        <npc id="23351"/>	<!--Дикое Дерево Хранитель-->
    </spawn>
    <spawn count="1" respawn="60" respawn_random="0" period_of_day="none">
        <point x="5773" y="-120736" z="-2088" h="5624"/>
        <npc id="23353"/>	<!--Дикий Хранитель-->
    </spawn>
    <spawn count="1" respawn="60" respawn_random="0" period_of_day="none">
        <point x="6991" y="-119150" z="-1792" h="20004"/>
        <npc id="23353"/>	<!--Дикий Хранитель-->
    </spawn>
    <spawn count="1" respawn="60" respawn_random="0" period_of_day="none">
        <point x="6523" y="-120573" z="-1944" h="48298"/>
        <npc id="23353"/>	<!--Дикий Хранитель-->
    </spawn>
    <spawn count="1" respawn="60" respawn_random="0" period_of_day="none">
        <point x="6273" y="-120573" z="-1976" h="47490"/>
        <npc id="23353"/>	<!--Дикий Хранитель-->
    </spawn>
    <spawn count="1" respawn="60" respawn_random="0" period_of_day="none">
        <point x="7533" y="-120813" z="-1784" h="41799"/>
        <npc id="23352"/>	<!--Дикое Дерево Тайник-->
    </spawn>
    <spawn count="1" respawn="60" respawn_random="0" period_of_day="none">
        <point x="6972" y="-120435" z="-1864" h="28565"/>
        <npc id="23352"/>	<!--Дикое Дерево Тайник-->
    </spawn>
    <spawn count="1" respawn="60" respawn_random="0" period_of_day="none">
        <point x="8201" y="-119780" z="-1784" h="32356"/>
        <npc id="23351"/>	<!--Дикое Дерево Хранитель-->
    </spawn>
    <spawn count="1" respawn="60" respawn_random="0" period_of_day="none">
        <point x="8201" y="-118310" z="-1760" h="49175"/>
        <npc id="23352"/>	<!--Дикое Дерево Тайник-->
    </spawn>
    <spawn count="1" respawn="60" respawn_random="0" period_of_day="none">
        <point x="9895" y="-118730" z="-1752" h="63233"/>
        <npc id="23353"/>	<!--Дикий Хранитель-->
    </spawn>
    <spawn count="1" respawn="60" respawn_random="0" period_of_day="none">
        <point x="8685" y="-118310" z="-1736" h="2147"/>
        <npc id="23352"/>	<!--Дикое Дерево Тайник-->
    </spawn>
    <spawn count="1" respawn="60" respawn_random="0" period_of_day="none">
        <point x="8685" y="-118100" z="-1736" h="4433"/>
        <npc id="23352"/>	<!--Дикое Дерево Тайник-->
    </spawn>
    <spawn count="1" respawn="60" respawn_random="0" period_of_day="none">
        <point x="8685" y="-118100" z="-1736" h="31450"/>
        <npc id="23351"/>	<!--Дикое Дерево Хранитель-->
    </spawn>
    <spawn count="1" respawn="60" respawn_random="0" period_of_day="none">
        <point x="5273" y="-122203" z="-2248" h="43615"/>
        <npc id="23353"/>	<!--Дикий Хранитель-->
    </spawn>
    <spawn count="1" respawn="60" respawn_random="0" period_of_day="none">
        <point x="4773" y="-121062" z="-2288" h="55633"/>
        <npc id="23351"/>	<!--Дикое Дерево Хранитель-->
    </spawn>
    <spawn count="1" respawn="60" respawn_random="0" period_of_day="none">
        <point x="5773" y="-121714" z="-2128" h="23104"/>
        <npc id="23352"/>	<!--Дикое Дерево Тайник-->
    </spawn>
    <spawn count="1" respawn="60" respawn_random="0" period_of_day="none">
        <point x="5773" y="-121714" z="-2128" h="6419"/>
        <npc id="23352"/>	<!--Дикое Дерево Тайник-->
    </spawn>
    <spawn count="1" respawn="60" respawn_random="0" period_of_day="none">
        <point x="5523" y="-121551" z="-2152" h="30587"/>
        <npc id="23351"/>	<!--Дикое Дерево Хранитель-->
    </spawn>
    <spawn count="1" respawn="60" respawn_random="0" period_of_day="none">
        <point x="6023" y="-121388" z="-2064" h="51571"/>
        <npc id="23352"/>	<!--Дикое Дерево Тайник-->
    </spawn>
    <spawn count="1" respawn="60" respawn_random="0" period_of_day="none">
        <point x="5773" y="-122366" z="-2232" h="28558"/>
        <npc id="23352"/>	<!--Дикое Дерево Тайник-->
    </spawn>
    <spawn count="1" respawn="60" respawn_random="0" period_of_day="none">
        <point x="5273" y="-121551" z="-2184" h="35436"/>
        <npc id="23351"/>	<!--Дикое Дерево Хранитель-->
    </spawn>
    <spawn count="1" respawn="60" respawn_random="0" period_of_day="none">
        <point x="7023" y="-121714" z="-1904" h="11496"/>
        <npc id="23352"/>	<!--Дикое Дерево Тайник-->
    </spawn>
    <spawn count="1" respawn="60" respawn_random="0" period_of_day="none">
        <point x="8023" y="-121551" z="-1776" h="4376"/>
        <npc id="23351"/>	<!--Дикое Дерево Хранитель-->
    </spawn>
    <spawn count="1" respawn="60" respawn_random="0" period_of_day="none">
        <point x="7773" y="-121225" z="-1776" h="15799"/>
        <npc id="23353"/>	<!--Дикий Хранитель-->
    </spawn>
    <spawn count="1" respawn="60" respawn_random="0" period_of_day="none">
        <point x="6523" y="-121388" z="-1960" h="1362"/>
        <npc id="23353"/>	<!--Дикий Хранитель-->
    </spawn>
    <spawn count="1" respawn="60" respawn_random="0" period_of_day="none">
        <point x="6523" y="-122692" z="-2224" h="44916"/>
        <npc id="23353"/>	<!--Дикий Хранитель-->
    </spawn>
    <spawn count="1" respawn="60" respawn_random="0" period_of_day="none">
        <point x="7273" y="-122040" z="-1928" h="45024"/>
        <npc id="23352"/>	<!--Дикое Дерево Тайник-->
    </spawn>
    <spawn count="1" respawn="60" respawn_random="0" period_of_day="none">
        <point x="8023" y="-122692" z="-1968" h="64836"/>
        <npc id="23353"/>	<!--Дикий Хранитель-->
    </spawn>
    <spawn count="1" respawn="60" respawn_random="0" period_of_day="none">
        <point x="7773" y="-122040" z="-1880" h="35188"/>
        <npc id="23352"/>	<!--Дикое Дерево Тайник-->
    </spawn>
    <spawn count="1" respawn="60" respawn_random="0" period_of_day="none">
        <point x="7023" y="-122203" z="-2008" h="42606"/>
        <npc id="23351"/>	<!--Дикое Дерево Хранитель-->
    </spawn>
    <spawn count="1" respawn="60" respawn_random="0" period_of_day="none">
        <point x="8023" y="-121714" z="-1792" h="41033"/>
        <npc id="23352"/>	<!--Дикое Дерево Тайник-->
    </spawn>
    <spawn count="1" respawn="60" respawn_random="0" period_of_day="none">
        <point x="7273" y="-122040" z="-1928" h="15922"/>
        <npc id="23351"/>	<!--Дикое Дерево Хранитель-->
    </spawn>
    <spawn count="1" respawn="60" respawn_random="0" period_of_day="none">
        <point x="7273" y="-120899" z="-1808" h="22522"/>
        <npc id="23351"/>	<!--Дикое Дерево Хранитель-->
    </spawn>
    <spawn count="1" respawn="60" respawn_random="0" period_of_day="none">
        <point x="8023" y="-122855" z="-1968" h="58633"/>
        <npc id="23351"/>	<!--Дикое Дерево Хранитель-->
    </spawn>
    <spawn count="1" respawn="60" respawn_random="0" period_of_day="none">
        <point x="7023" y="-120899" z="-1848" h="3462"/>
        <npc id="23351"/>	<!--Дикое Дерево Хранитель-->
    </spawn>
    <spawn count="1" respawn="60" respawn_random="0" period_of_day="none">
        <point x="7907" y="-121002" z="-1760" h="57326"/>
        <npc id="23353"/>	<!--Дикий Хранитель-->
    </spawn>
    <spawn count="1" respawn="60" respawn_random="0" period_of_day="none">
        <point x="7720" y="-121002" z="-1760" h="30979"/>
        <npc id="23351"/>	<!--Дикое Дерево Хранитель-->
    </spawn>
    <spawn count="1" respawn="60" respawn_random="0" period_of_day="none">
        <point x="9023" y="-122692" z="-1704" h="18582"/>
        <npc id="23353"/>	<!--Дикий Хранитель-->
    </spawn>
    <spawn count="1" respawn="60" respawn_random="0" period_of_day="none">
        <point x="8773" y="-122203" z="-1712" h="57203"/>
        <npc id="23353"/>	<!--Дикий Хранитель-->
    </spawn>
    <spawn count="1" respawn="60" respawn_random="0" period_of_day="none">
        <point x="8273" y="-122692" z="-1904" h="40285"/>
        <npc id="23352"/>	<!--Дикое Дерево Тайник-->
    </spawn>
    <spawn count="1" respawn="60" respawn_random="0" period_of_day="none">
        <point x="9029" y="-121947" z="-1664" h="14935"/>
        <npc id="23353"/>	<!--Дикий Хранитель-->
    </spawn>
    <spawn count="1" respawn="60" respawn_random="0" period_of_day="none">
        <point x="9590" y="-122703" z="-1640" h="5299"/>
        <npc id="23351"/>	<!--Дикое Дерево Хранитель-->
    </spawn>
    <spawn count="1" respawn="60" respawn_random="0" period_of_day="none">
        <point x="8281" y="-121380" z="-1736" h="14465"/>
        <npc id="23352"/>	<!--Дикое Дерево Тайник-->
    </spawn>
    <spawn count="1" respawn="60" respawn_random="0" period_of_day="none">
        <point x="8655" y="-122514" z="-1792" h="55917"/>
        <npc id="23351"/>	<!--Дикое Дерево Хранитель-->
    </spawn>
    <spawn count="1" respawn="60" respawn_random="0" period_of_day="none">
        <point x="8842" y="-122703" z="-1768" h="61269"/>
        <npc id="23351"/>	<!--Дикое Дерево Хранитель-->
    </spawn>
    <spawn count="1" respawn="60" respawn_random="0" period_of_day="none">
        <point x="10379" y="-120200" z="-1680" h="44100"/>
        <npc id="23351"/>	<!--Дикое Дерево Хранитель-->
    </spawn>
    <spawn count="1" respawn="60" respawn_random="0" period_of_day="none">
        <point x="6856" y="-124788" z="-2344" h="50799"/>
        <npc id="23351"/>	<!--Дикое Дерево Хранитель-->
    </spawn>
    <spawn count="1" respawn="60" respawn_random="0" period_of_day="none">
        <point x="7907" y="-123081" z="-2032" h="13578"/>
        <npc id="23353"/>	<!--Дикий Хранитель-->
    </spawn>
    <spawn count="1" respawn="60" respawn_random="0" period_of_day="none">
        <point x="8523" y="-123181" z="-1904" h="47566"/>
        <npc id="23352"/>	<!--Дикое Дерево Тайник-->
    </spawn>
    <spawn count="1" respawn="60" respawn_random="0" period_of_day="none">
        <point x="8523" y="-123181" z="-1904" h="60919"/>
        <npc id="23351"/>	<!--Дикое Дерево Хранитель-->
    </spawn>
    <spawn count="1" respawn="60" respawn_random="0" period_of_day="none">
        <point x="9590" y="-123648" z="-1712" h="51448"/>
        <npc id="23353"/>	<!--Дикий Хранитель-->
    </spawn>
    <spawn count="1" respawn="60" respawn_random="0" period_of_day="none">
        <point x="8468" y="-123648" z="-2000" h="63426"/>
        <npc id="23352"/>	<!--Дикое Дерево Тайник-->
    </spawn>
    <spawn count="1" respawn="60" respawn_random="0" period_of_day="none">
        <point x="11636" y="-124104" z="-1416" h="34837"/>
        <npc id="23352"/>	<!--Дикое Дерево Тайник-->
    </spawn>
    <spawn count="1" respawn="60" respawn_random="0" period_of_day="none">
        <point x="12269" y="-124756" z="-1376" h="27336"/>
        <npc id="23353"/>	<!--Дикий Хранитель-->
    </spawn>
    <spawn count="1" respawn="60" respawn_random="0" period_of_day="none">
        <point x="12269" y="-123615" z="-1304" h="32513"/>
        <npc id="23352"/>	<!--Дикое Дерево Тайник-->
    </spawn>
    <spawn count="1" respawn="60" respawn_random="0" period_of_day="none">
        <point x="4256" y="-124376" z="-2792" h="23399"/>
        <npc id="23351"/>	<!--Дикое Дерево Хранитель-->
    </spawn>
    <spawn count="1" respawn="60" respawn_random="0" period_of_day="none">
        <point x="5816" y="-124788" z="-2608" h="59323"/>
        <npc id="23353"/>	<!--Дикий Хранитель-->
    </spawn>
    <spawn count="1" respawn="60" respawn_random="0" period_of_day="none">
        <point x="4781" y="-123581" z="-2592" h="51229"/>
        <npc id="23352"/>	<!--Дикое Дерево Тайник-->
    </spawn>
    <spawn count="1" respawn="60" respawn_random="0" period_of_day="none">
        <point x="5816" y="-125612" z="-2688" h="18133"/>
        <npc id="23353"/>	<!--Дикий Хранитель-->
    </spawn>
    <spawn count="1" respawn="60" respawn_random="0" period_of_day="none">
        <point x="4776" y="-126436" z="-3000" h="6944"/>
        <npc id="23352"/>	<!--Дикое Дерево Тайник-->
    </spawn>
    <spawn count="1" respawn="60" respawn_random="0" period_of_day="none">
        <point x="4256" y="-126024" z="-3048" h="47722"/>
        <npc id="23352"/>	<!--Дикое Дерево Тайник-->
    </spawn>
    <spawn count="1" respawn="60" respawn_random="0" period_of_day="none">
        <point x="4256" y="-126024" z="-3048" h="40309"/>
        <npc id="23352"/>	<!--Дикое Дерево Тайник-->
    </spawn>
    <spawn count="1" respawn="60" respawn_random="0" period_of_day="none">
        <point x="6856" y="-126024" z="-2560" h="62781"/>
        <npc id="23353"/>	<!--Дикий Хранитель-->
    </spawn>
    <spawn count="1" respawn="60" respawn_random="0" period_of_day="none">
        <point x="6856" y="-125612" z="-2520" h="56409"/>
        <npc id="23352"/>	<!--Дикое Дерево Тайник-->
    </spawn>
    <spawn count="1" respawn="60" respawn_random="0" period_of_day="none">
        <point x="6336" y="-126436" z="-2696" h="63720"/>
        <npc id="23352"/>	<!--Дикое Дерево Тайник-->
    </spawn>
    <spawn count="1" respawn="60" respawn_random="0" period_of_day="none">
        <point x="2176" y="-126848" z="-3176" h="61240"/>
        <npc id="23353"/>	<!--Дикий Хранитель-->
    </spawn>
    <spawn count="1" respawn="60" respawn_random="0" period_of_day="none">
        <point x="2176" y="-126024" z="-3304" h="46953"/>
        <npc id="23352"/>	<!--Дикое Дерево Тайник-->
    </spawn>
    <spawn count="1" respawn="60" respawn_random="0" period_of_day="none">
        <point x="2176" y="-124788" z="-3200" h="56901"/>
        <npc id="23351"/>	<!--Дикое Дерево Хранитель-->
    </spawn>
    <spawn count="1" respawn="60" respawn_random="0" period_of_day="none">
        <point x="2694" y="-122023" z="-2680" h="20415"/>
        <npc id="23353"/>	<!--Дикий Хранитель-->
    </spawn>
    <spawn count="1" respawn="60" respawn_random="0" period_of_day="none">
        <point x="2694" y="-120973" z="-2648" h="59368"/>
        <npc id="23353"/>	<!--Дикий Хранитель-->
    </spawn>
    <spawn count="1" respawn="60" respawn_random="0" period_of_day="none">
        <point x="2537" y="-121918" z="-2712" h="55453"/>
        <npc id="23352"/>	<!--Дикое Дерево Тайник-->
    </spawn>
    <spawn count="1" respawn="60" respawn_random="0" period_of_day="none">
        <point x="2223" y="-121498" z="-2728" h="8718"/>
        <npc id="23353"/>	<!--Дикий Хранитель-->
    </spawn>
    <spawn count="1" respawn="60" respawn_random="0" period_of_day="none">
        <point x="2537" y="-121078" z="-2672" h="51245"/>
        <npc id="23352"/>	<!--Дикое Дерево Тайник-->
    </spawn>
    <spawn count="1" respawn="60" respawn_random="0" period_of_day="none">
        <point x="2066" y="-121603" z="-2752" h="36746"/>
        <npc id="23352"/>	<!--Дикое Дерево Тайник-->
    </spawn>
    <spawn count="1" respawn="60" respawn_random="0" period_of_day="none">
        <point x="3165" y="-120973" z="-2600" h="17399"/>
        <npc id="23353"/>	<!--Дикий Хранитель-->
    </spawn>
    <spawn count="1" respawn="60" respawn_random="0" period_of_day="none">
        <point x="2851" y="-121393" z="-2632" h="60425"/>
        <npc id="23353"/>	<!--Дикий Хранитель-->
    </spawn>
    <spawn count="1" respawn="60" respawn_random="0" period_of_day="none">
        <point x="2851" y="-122128" z="-2656" h="23829"/>
        <npc id="23352"/>	<!--Дикое Дерево Тайник-->
    </spawn>
    <spawn count="1" respawn="60" respawn_random="0" period_of_day="none">
        <point x="2851" y="-120973" z="-2632" h="27879"/>
        <npc id="23352"/>	<!--Дикое Дерево Тайник-->
    </spawn>
    <spawn count="1" respawn="60" respawn_random="0" period_of_day="none">
        <point x="2223" y="-121708" z="-2736" h="48544"/>
        <npc id="23352"/>	<!--Дикое Дерево Тайник-->
    </spawn>
    <spawn count="1" respawn="60" respawn_random="0" period_of_day="none">
        <point x="2380" y="-121918" z="-2728" h="18877"/>
        <npc id="23351"/>	<!--Дикое Дерево Хранитель-->
    </spawn>
    <spawn count="1" respawn="60" respawn_random="0" period_of_day="none">
        <point x="3008" y="-121813" z="-2624" h="60812"/>
        <npc id="23352"/>	<!--Дикое Дерево Тайник-->
    </spawn>
    <spawn count="1" respawn="60" respawn_random="0" period_of_day="none">
        <point x="2851" y="-122023" z="-2656" h="51183"/>
        <npc id="23351"/>	<!--Дикое Дерево Хранитель-->
    </spawn>
    <spawn count="1" respawn="60" respawn_random="0" period_of_day="none">
        <point x="1656" y="-125612" z="-3304" h="36043"/>
        <npc id="23351"/>	<!--Дикое Дерево Хранитель-->
    </spawn>
    <spawn count="1" respawn="60" respawn_random="0" period_of_day="none">
        <point x="1656" y="-125200" z="-3256" h="9944"/>
        <npc id="23351"/>	<!--Дикое Дерево Хранитель-->
    </spawn>
    <spawn count="1" respawn="60" respawn_random="0" period_of_day="none">
        <point x="1909" y="-122338" z="-2808" h="27146"/>
        <npc id="23352"/>	<!--Дикое Дерево Тайник-->
    </spawn>
    <spawn count="1" respawn="60" respawn_random="0" period_of_day="none">
        <point x="1124" y="-122443" z="-2968" h="46998"/>
        <npc id="23353"/>	<!--Дикий Хранитель-->
    </spawn>
    <spawn count="1" respawn="60" respawn_random="0" period_of_day="none">
        <point x="1909" y="-121498" z="-2792" h="38838"/>
        <npc id="23353"/>	<!--Дикий Хранитель-->
    </spawn>
    <spawn count="1" respawn="60" respawn_random="0" period_of_day="none">
        <point x="653" y="-121393" z="-2912" h="44390"/>
        <npc id="23353"/>	<!--Дикий Хранитель-->
    </spawn>
    <spawn count="1" respawn="60" respawn_random="0" period_of_day="none">
        <point x="1124" y="-121393" z="-2904" h="30965"/>
        <npc id="23353"/>	<!--Дикий Хранитель-->
    </spawn>
    <spawn count="1" respawn="60" respawn_random="0" period_of_day="none">
        <point x="653" y="-121603" z="-2936" h="60614"/>
        <npc id="23353"/>	<!--Дикий Хранитель-->
    </spawn>
    <spawn count="1" respawn="60" respawn_random="0" period_of_day="none">
        <point x="1595" y="-121393" z="-2824" h="22535"/>
        <npc id="23351"/>	<!--Дикое Дерево Хранитель-->
    </spawn>
    <spawn count="1" respawn="60" respawn_random="0" period_of_day="none">
        <point x="810" y="-120868" z="-2864" h="38098"/>
        <npc id="23352"/>	<!--Дикое Дерево Тайник-->
    </spawn>
    <spawn count="1" respawn="60" respawn_random="0" period_of_day="none">
        <point x="496" y="-122023" z="-2976" h="15616"/>
        <npc id="23351"/>	<!--Дикое Дерево Хранитель-->
    </spawn>
    <spawn count="1" respawn="60" respawn_random="0" period_of_day="none">
        <point x="496" y="-120973" z="-2864" h="50139"/>
        <npc id="23352"/>	<!--Дикое Дерево Тайник-->
    </spawn>
    <spawn count="1" respawn="60" respawn_random="0" period_of_day="none">
        <point x="1595" y="-121498" z="-2824" h="32603"/>
        <npc id="23351"/>	<!--Дикое Дерево Хранитель-->
    </spawn>
    <spawn count="1" respawn="60" respawn_random="0" period_of_day="none">
        <point x="1909" y="-121393" z="-2784" h="41748"/>
        <npc id="23351"/>	<!--Дикое Дерево Хранитель-->
    </spawn>
    <spawn count="1" respawn="60" respawn_random="0" period_of_day="none">
        <point x="1438" y="-122233" z="-2872" h="64627"/>
        <npc id="23351"/>	<!--Дикое Дерево Хранитель-->
    </spawn>
    <spawn count="1" respawn="60" respawn_random="0" period_of_day="none">
        <point x="496" y="-120973" z="-2864" h="47323"/>
        <npc id="23351"/>	<!--Дикое Дерево Хранитель-->
    </spawn>
    <spawn count="1" respawn="60" respawn_random="0" period_of_day="none">
        <point x="810" y="-120973" z="-2880" h="37816"/>
        <npc id="23351"/>	<!--Дикое Дерево Хранитель-->
    </spawn>
    <spawn count="1" respawn="60" respawn_random="0" period_of_day="none">
        <point x="2066" y="-120658" z="-2720" h="47530"/>
        <npc id="23351"/>	<!--Дикое Дерево Хранитель-->
    </spawn>
    <spawn count="1" respawn="60" respawn_random="0" period_of_day="none">
        <point x="983" y="-117750" z="-2520" h="36931"/>
        <npc id="23353"/>	<!--Дикий Хранитель-->
    </spawn>
    <spawn count="1" respawn="60" respawn_random="0" period_of_day="none">
        <point x="652" y="-117018" z="-2432" h="38248"/>
        <npc id="23353"/>	<!--Дикий Хранитель-->
    </spawn>
    <spawn count="1" respawn="60" respawn_random="0" period_of_day="none">
        <point x="839" y="-118019" z="-2560" h="14592"/>
        <npc id="23352"/>	<!--Дикое Дерево Тайник-->
    </spawn>
    <spawn count="1" respawn="60" respawn_random="0" period_of_day="none">
        <point x="839" y="-118305" z="-2616" h="43563"/>
        <npc id="23352"/>	<!--Дикое Дерево Тайник-->
    </spawn>
    <spawn count="1" respawn="60" respawn_random="0" period_of_day="none">
        <point x="465" y="-118162" z="-2576" h="6280"/>
        <npc id="23352"/>	<!--Дикое Дерево Тайник-->
    </spawn>
    <spawn count="1" respawn="60" respawn_random="0" period_of_day="none">
        <point x="1774" y="-117304" z="-2480" h="44017"/>
        <npc id="23351"/>	<!--Дикое Дерево Хранитель-->
    </spawn>
    <spawn count="1" respawn="60" respawn_random="0" period_of_day="none">
        <point x="839" y="-117733" z="-2520" h="1927"/>
        <npc id="23351"/>	<!--Дикое Дерево Хранитель-->
    </spawn>
    <spawn count="1" respawn="60" respawn_random="0" period_of_day="none">
        <point x="1167" y="-117896" z="-2552" h="37203"/>
        <npc id="23351"/>	<!--Дикое Дерево Хранитель-->
    </spawn>
    <spawn count="1" respawn="60" respawn_random="0" period_of_day="none">
        <point x="6265" y="-109485" z="-1880" h="25726"/>
        <npc id="23352"/>	<!--Дикое Дерево Тайник-->
    </spawn>
    <spawn count="1" respawn="60" respawn_random="0" period_of_day="none">
        <point x="6501" y="-110345" z="-1760" h="7795"/>
        <npc id="23353"/>	<!--Дикий Хранитель-->
    </spawn>
    <spawn count="1" respawn="60" respawn_random="0" period_of_day="none">
        <point x="6501" y="-109915" z="-1784" h="2517"/>
        <npc id="23352"/>	<!--Дикое Дерево Тайник-->
    </spawn>
    <spawn count="1" respawn="60" respawn_random="0" period_of_day="none">
        <point x="7445" y="-109055" z="-1736" h="64614"/>
        <npc id="23353"/>	<!--Дикий Хранитель-->
    </spawn>
    <spawn count="1" respawn="60" respawn_random="0" period_of_day="none">
        <point x="7445" y="-110345" z="-1736" h="11609"/>
        <npc id="23352"/>	<!--Дикое Дерево Тайник-->
    </spawn>
    <spawn count="1" respawn="60" respawn_random="0" period_of_day="none">
        <point x="7445" y="-108625" z="-1744" h="17163"/>
        <npc id="23352"/>	<!--Дикое Дерево Тайник-->
    </spawn>
    <spawn count="1" respawn="60" respawn_random="0" period_of_day="none">
        <point x="7681" y="-109915" z="-1736" h="44200"/>
        <npc id="23352"/>	<!--Дикое Дерево Тайник-->
    </spawn>
    <spawn count="1" respawn="60" respawn_random="0" period_of_day="none">
        <point x="6973" y="-109055" z="-1792" h="21358"/>
        <npc id="23351"/>	<!--Дикое Дерево Хранитель-->
    </spawn>
    <spawn count="1" respawn="60" respawn_random="0" period_of_day="none">
        <point x="7445" y="-108625" z="-1744" h="3369"/>
        <npc id="23351"/>	<!--Дикое Дерево Хранитель-->
    </spawn>
    <spawn count="1" respawn="60" respawn_random="0" period_of_day="none">
        <point x="11215" y="-112584" z="-1680" h="52660"/>
        <npc id="23353"/>	<!--Дикий Хранитель-->
    </spawn>
    <spawn count="1" respawn="60" respawn_random="0" period_of_day="none">
        <point x="11725" y="-112584" z="-1680" h="54108"/>
        <npc id="23352"/>	<!--Дикое Дерево Тайник-->
    </spawn>
    <spawn count="1" respawn="60" respawn_random="0" period_of_day="none">
        <point x="11810" y="-112246" z="-1672" h="19399"/>
        <npc id="23351"/>	<!--Дикое Дерево Хранитель-->
    </spawn>
    <spawn count="1" respawn="60" respawn_random="0" period_of_day="none">
        <point x="10960" y="-111570" z="-1680" h="44297"/>
        <npc id="23352"/>	<!--Дикое Дерево Тайник-->
    </spawn>
    <spawn count="1" respawn="60" respawn_random="0" period_of_day="none">
        <point x="11470" y="-112584" z="-1680" h="36372"/>
        <npc id="23352"/>	<!--Дикое Дерево Тайник-->
    </spawn>
    <spawn count="1" respawn="60" respawn_random="0" period_of_day="none">
        <point x="11895" y="-113598" z="-1664" h="1916"/>
        <npc id="23353"/>	<!--Дикий Хранитель-->
    </spawn>
    <spawn count="1" respawn="60" respawn_random="0" period_of_day="none">
        <point x="11470" y="-113767" z="-1680" h="30156"/>
        <npc id="23352"/>	<!--Дикое Дерево Тайник-->
    </spawn>
    <spawn count="1" respawn="60" respawn_random="0" period_of_day="none">
        <point x="10875" y="-113091" z="-1680" h="22276"/>
        <npc id="23353"/>	<!--Дикий Хранитель-->
    </spawn>
    <spawn count="1" respawn="60" respawn_random="0" period_of_day="none">
        <point x="10960" y="-114105" z="-1680" h="41236"/>
        <npc id="23351"/>	<!--Дикое Дерево Хранитель-->
    </spawn>
    <spawn count="1" respawn="60" respawn_random="0" period_of_day="none">
        <point x="11470" y="-114443" z="-1680" h="44650"/>
        <npc id="23353"/>	<!--Дикий Хранитель-->
    </spawn>
    <spawn count="1" respawn="60" respawn_random="0" period_of_day="none">
        <point x="11725" y="-113429" z="-1672" h="18587"/>
        <npc id="23351"/>	<!--Дикое Дерево Хранитель-->
    </spawn>
    <spawn count="1" respawn="60" respawn_random="0" period_of_day="none">
        <point x="11130" y="-113936" z="-1680" h="64702"/>
        <npc id="23351"/>	<!--Дикое Дерево Хранитель-->
    </spawn>
    <spawn count="1" respawn="60" respawn_random="0" period_of_day="none">
        <point x="21171" y="-107730" z="-3040" h="30000"/>
        <npc id="30649"/>	<!--Прародитель Мартанкус-->
    </spawn>
    <spawn count="1" respawn="60" respawn_random="0" period_of_day="none">
        <point x="2398" y="-99593" z="-1840" h="3402"/>
        <npc id="23353"/>	<!--Дикий Хранитель-->
    </spawn>
    <spawn count="1" respawn="60" respawn_random="0" period_of_day="none">
        <point x="21268" y="-124703" z="-464" h="49531"/>
        <npc id="23353"/>	<!--Дикий Хранитель-->
    </spawn>
    <spawn count="1" respawn="60" respawn_random="0" period_of_day="none">
        <point x="21209" y="-124541" z="-480" h="55958"/>
        <npc id="23352"/>	<!--Дикое Дерево Тайник-->
    </spawn>
    <spawn count="1" respawn="60" respawn_random="0" period_of_day="none">
        <point x="21032" y="-124541" z="-472" h="10712"/>
        <npc id="23353"/>	<!--Дикий Хранитель-->
    </spawn>
    <spawn count="1" respawn="60" respawn_random="0" period_of_day="none">
        <point x="22451" y="-120979" z="-664" h="82"/>
        <npc id="23352"/>	<!--Дикое Дерево Тайник-->
    </spawn>
    <spawn count="1" respawn="60" respawn_random="0" period_of_day="none">
        <point x="22089" y="-122771" z="-704" h="9967"/>
        <npc id="23353"/>	<!--Дикий Хранитель-->
    </spawn>
    <spawn count="1" respawn="60" respawn_random="0" period_of_day="none">
        <point x="21184" y="-120851" z="-568" h="1620"/>
        <npc id="23352"/>	<!--Дикое Дерево Тайник-->
    </spawn>
    <spawn count="1" respawn="60" respawn_random="0" period_of_day="none">
        <point x="21546" y="-120851" z="-608" h="24513"/>
        <npc id="23351"/>	<!--Дикое Дерево Хранитель-->
    </spawn>
    <spawn count="1" respawn="60" respawn_random="0" period_of_day="none">
        <point x="21908" y="-122387" z="-632" h="15894"/>
        <npc id="23353"/>	<!--Дикий Хранитель-->
    </spawn>
    <spawn count="1" respawn="60" respawn_random="0" period_of_day="none">
        <point x="20822" y="-121363" z="-664" h="50902"/>
        <npc id="23351"/>	<!--Дикое Дерево Хранитель-->
    </spawn>
    <spawn count="1" respawn="60" respawn_random="0" period_of_day="none">
        <point x="22089" y="-121747" z="-576" h="7318"/>
        <npc id="23351"/>	<!--Дикое Дерево Хранитель-->
    </spawn>
    <spawn count="1" respawn="60" respawn_random="0" period_of_day="none">
        <point x="24230" y="-123932" z="-616" h="15680"/>
        <npc id="23352"/>	<!--Дикое Дерево Тайник-->
    </spawn>
    <spawn count="1" respawn="60" respawn_random="0" period_of_day="none">
        <point x="24132" y="-124751" z="-696" h="13748"/>
        <npc id="23353"/>	<!--Дикий Хранитель-->
    </spawn>
    <spawn count="1" respawn="60" respawn_random="0" period_of_day="none">
        <point x="24524" y="-123841" z="-616" h="12456"/>
        <npc id="23352"/>	<!--Дикое Дерево Тайник-->
    </spawn>
    <spawn count="1" respawn="60" respawn_random="0" period_of_day="none">
        <point x="24426" y="-124205" z="-672" h="57453"/>
        <npc id="23352"/>	<!--Дикое Дерево Тайник-->
    </spawn>
    <spawn count="1" respawn="60" respawn_random="0" period_of_day="none">
        <point x="24328" y="-124569" z="-704" h="36880"/>
        <npc id="23353"/>	<!--Дикий Хранитель-->
    </spawn>
    <spawn count="1" respawn="60" respawn_random="0" period_of_day="none">
        <point x="23642" y="-124660" z="-664" h="23881"/>
        <npc id="23353"/>	<!--Дикий Хранитель-->
    </spawn>
    <spawn count="1" respawn="60" respawn_random="0" period_of_day="none">
        <point x="23054" y="-124751" z="-632" h="56627"/>
        <npc id="23353"/>	<!--Дикий Хранитель-->
    </spawn>
    <spawn count="1" respawn="60" respawn_random="0" period_of_day="none">
        <point x="23936" y="-124751" z="-704" h="58192"/>
        <npc id="23351"/>	<!--Дикое Дерево Хранитель-->
    </spawn>
    <spawn count="1" respawn="60" respawn_random="0" period_of_day="none">
        <point x="23838" y="-123841" z="-560" h="6503"/>
        <npc id="23351"/>	<!--Дикое Дерево Хранитель-->
    </spawn>
    <spawn count="1" respawn="60" respawn_random="0" period_of_day="none">
        <point x="24132" y="-124205" z="-648" h="2242"/>
        <npc id="23351"/>	<!--Дикое Дерево Хранитель-->
    </spawn>
    <spawn count="1" respawn="60" respawn_random="0" period_of_day="none">
        <point x="24328" y="-124751" z="-704" h="63993"/>
        <npc id="23351"/>	<!--Дикое Дерево Хранитель-->
    </spawn>
    <spawn count="1" respawn="60" respawn_random="0" period_of_day="none">
        <point x="23718" y="-121363" z="-704" h="56061"/>
        <npc id="23351"/>	<!--Дикое Дерево Хранитель-->
    </spawn>
    <spawn count="1" respawn="60" respawn_random="0" period_of_day="none">
        <point x="22632" y="-121363" z="-656" h="45714"/>
        <npc id="23353"/>	<!--Дикий Хранитель-->
    </spawn>
    <spawn count="1" respawn="60" respawn_random="0" period_of_day="none">
        <point x="22632" y="-122643" z="-744" h="24375"/>
        <npc id="23352"/>	<!--Дикое Дерево Тайник-->
    </spawn>
    <spawn count="1" respawn="60" respawn_random="0" period_of_day="none">
        <point x="24622" y="-124569" z="-712" h="19084"/>
        <npc id="23352"/>	<!--Дикое Дерево Тайник-->
    </spawn>
    <spawn count="1" respawn="60" respawn_random="0" period_of_day="none">
        <point x="26828" y="-125028" z="-752" h="23536"/>
        <npc id="32056"/>	<!--Арен-->
    </spawn>
    <spawn count="1" respawn="60" respawn_random="0" period_of_day="none">
        <point x="17236" y="-127609" z="-2832" h="50530"/>
        <npc id="23352"/>	<!--Дикое Дерево Тайник-->
    </spawn>
    <spawn count="1" respawn="60" respawn_random="0" period_of_day="none">
        <point x="16721" y="-128445" z="-2792" h="21528"/>
        <npc id="23353"/>	<!--Дикий Хранитель-->
    </spawn>
    <spawn count="1" respawn="60" respawn_random="0" period_of_day="none">
        <point x="16927" y="-128236" z="-2784" h="51050"/>
        <npc id="23352"/>	<!--Дикое Дерево Тайник-->
    </spawn>
    <spawn count="1" respawn="60" respawn_random="0" period_of_day="none">
        <point x="14590" y="-125245" z="-1152" h="46593"/>
        <npc id="23351"/>	<!--Дикое Дерево Хранитель-->
    </spawn>
    <spawn count="1" respawn="60" respawn_random="0" period_of_day="none">
        <point x="16515" y="-125937" z="-2920" h="40038"/>
        <npc id="23352"/>	<!--Дикое Дерево Тайник-->
    </spawn>
    <spawn count="1" respawn="60" respawn_random="0" period_of_day="none">
        <point x="17442" y="-125519" z="-2952" h="57001"/>
        <npc id="23352"/>	<!--Дикое Дерево Тайник-->
    </spawn>
    <spawn count="1" respawn="60" respawn_random="0" period_of_day="none">
        <point x="16824" y="-126355" z="-2872" h="33348"/>
        <npc id="23351"/>	<!--Дикое Дерево Хранитель-->
    </spawn>
    <spawn count="1" respawn="60" respawn_random="0" period_of_day="none">
        <point x="17236" y="-125519" z="-2952" h="46760"/>
        <npc id="23353"/>	<!--Дикий Хранитель-->
    </spawn>
    <spawn count="1" respawn="60" respawn_random="0" period_of_day="none">
        <point x="17648" y="-125310" z="-3000" h="3634"/>
        <npc id="23351"/>	<!--Дикое Дерево Хранитель-->
    </spawn>
    <spawn count="1" respawn="60" respawn_random="0" period_of_day="none">
        <point x="16832" y="-125150" z="-3024" h="50856"/>
        <npc id="23351"/>	<!--Дикое Дерево Хранитель-->
    </spawn>
    <spawn count="1" respawn="60" respawn_random="0" period_of_day="none">
        <point x="10496" y="-130556" z="-2000" h="47268"/>
        <npc id="23351"/>	<!--Дикое Дерево Хранитель-->
    </spawn>
    <spawn count="1" respawn="60" respawn_random="0" period_of_day="none">
        <point x="13324" y="-125734" z="-1200" h="20508"/>
        <npc id="23353"/>	<!--Дикий Хранитель-->
    </spawn>
    <spawn count="1" respawn="60" respawn_random="0" period_of_day="none">
        <point x="12480" y="-125082" z="-1352" h="30287"/>
        <npc id="23351"/>	<!--Дикое Дерево Хранитель-->
    </spawn>
    <spawn count="1" respawn="60" respawn_random="0" period_of_day="none">
        <point x="13324" y="-125897" z="-1208" h="19766"/>
        <npc id="23351"/>	<!--Дикое Дерево Хранитель-->
    </spawn>
    <spawn count="1" respawn="60" respawn_random="0" period_of_day="none">
        <point x="12480" y="-123941" z="-1296" h="39055"/>
        <npc id="23353"/>	<!--Дикий Хранитель-->
    </spawn>
    <spawn count="1" respawn="60" respawn_random="0" period_of_day="none">
        <point x="12902" y="-124267" z="-1264" h="25754"/>
        <npc id="23352"/>	<!--Дикое Дерево Тайник-->
    </spawn>
    <spawn count="1" respawn="60" respawn_random="0" period_of_day="none">
        <point x="1136" y="-129320" z="-2808" h="62985"/>
        <npc id="23351"/>	<!--Дикое Дерево Хранитель-->
    </spawn>
    <spawn count="1" respawn="60" respawn_random="0" period_of_day="none">
        <point x="1656" y="-128908" z="-2840" h="21779"/>
        <npc id="23352"/>	<!--Дикое Дерево Тайник-->
    </spawn>
    <spawn count="1" respawn="60" respawn_random="0" period_of_day="none">
        <point x="3216" y="-129732" z="-3232" h="49165"/>
        <npc id="23352"/>	<!--Дикое Дерево Тайник-->
    </spawn>
    <spawn count="1" respawn="60" respawn_random="0" period_of_day="none">
        <point x="3736" y="-129732" z="-3256" h="10656"/>
        <npc id="23351"/>	<!--Дикое Дерево Хранитель-->
    </spawn>
    <spawn count="1" respawn="60" respawn_random="0" period_of_day="none">
        <point x="2176" y="-128084" z="-2968" h="33637"/>
        <npc id="23353"/>	<!--Дикий Хранитель-->
    </spawn>
    <spawn count="1" respawn="60" respawn_random="0" period_of_day="none">
        <point x="3736" y="-127672" z="-3128" h="46227"/>
        <npc id="23353"/>	<!--Дикий Хранитель-->
    </spawn>
    <spawn count="1" respawn="60" respawn_random="0" period_of_day="none">
        <point x="3736" y="-128084" z="-3144" h="48111"/>
        <npc id="23352"/>	<!--Дикое Дерево Тайник-->
    </spawn>
    <spawn count="1" respawn="60" respawn_random="0" period_of_day="none">
        <point x="7376" y="-129732" z="-2936" h="42165"/>
        <npc id="23353"/>	<!--Дикий Хранитель-->
    </spawn>
    <spawn count="1" respawn="60" respawn_random="0" period_of_day="none">
        <point x="7896" y="-129732" z="-2864" h="61917"/>
        <npc id="23351"/>	<!--Дикое Дерево Хранитель-->
    </spawn>
    <spawn count="1" respawn="60" respawn_random="0" period_of_day="none">
        <point x="8936" y="-129732" z="-2560" h="18838"/>
        <npc id="23353"/>	<!--Дикий Хранитель-->
    </spawn>
    <spawn count="1" respawn="60" respawn_random="0" period_of_day="none">
        <point x="8936" y="-129320" z="-2568" h="29020"/>
        <npc id="23353"/>	<!--Дикий Хранитель-->
    </spawn>
    <spawn count="1" respawn="60" respawn_random="0" period_of_day="none">
        <point x="9456" y="-129732" z="-2368" h="49759"/>
        <npc id="23352"/>	<!--Дикое Дерево Тайник-->
    </spawn>
    <spawn count="1" respawn="60" respawn_random="0" period_of_day="none">
        <point x="4338" y="-127707" z="-3128" h="28452"/>
        <npc id="23352"/>	<!--Дикое Дерево Тайник-->
    </spawn>
    <spawn count="1" respawn="60" respawn_random="0" period_of_day="none">
        <point x="5296" y="-127260" z="-3008" h="52224"/>
        <npc id="23351"/>	<!--Дикое Дерево Хранитель-->
    </spawn>
    <spawn count="1" respawn="60" respawn_random="0" period_of_day="none">
        <point x="6856" y="-127672" z="-2792" h="56399"/>
        <npc id="23351"/>	<!--Дикое Дерево Хранитель-->
    </spawn>
    <spawn count="1" respawn="60" respawn_random="0" period_of_day="none">
        <point x="6515" y="-127836" z="-2912" h="57806"/>
        <npc id="23351"/>	<!--Дикое Дерево Хранитель-->
    </spawn>
    <spawn count="1" respawn="60" respawn_random="0" period_of_day="none">
        <point x="8936" y="-127672" z="-2456" h="21396"/>
        <npc id="23353"/>	<!--Дикий Хранитель-->
    </spawn>
    <spawn count="1" respawn="90" respawn_random="0" period_of_day="none" group="assassing_kainak">
        <point x="15651" y="-112293" z="-232" h="13157"/>
        <npc id="19471"/>	<!--Таинственный Ассасин-->
    </spawn>
    <spawn count="1" respawn="90" respawn_random="0" period_of_day="none" group="assassing_kainak">
        <point x="15651" y="-112244" z="-232" h="25218"/>
        <npc id="19472"/>	<!--Таинственный Ассасин-->
    </spawn>
    <spawn count="1" respawn="90" respawn_random="0" period_of_day="none" group="assassing_kainak">
        <point x="15762" y="-112636" z="-240" h="7229"/>
        <npc id="19473"/>	<!--Таинственный Ассасин-->
    </spawn>
    <spawn count="1" respawn="90" respawn_random="0" period_of_day="none" group="assassing_kainak">
        <point x="15747" y="-113182" z="-248" h="13157"/>
        <npc id="19471"/>	<!--Таинственный Ассасин-->
    </spawn>
    <spawn count="1" respawn="90" respawn_random="0" period_of_day="none" group="assassing_kainak">
        <point x="15664" y="-113213" z="-250" h="25218"/>
        <npc id="19472"/>	<!--Таинственный Ассасин-->
    </spawn>
    <spawn count="1" respawn="90" respawn_random="0" period_of_day="none" group="assassing_kainak">
        <point x="15771" y="-113294" z="-250" h="7229"/>
        <npc id="19473"/>	<!--Таинственный Ассасин-->
    </spawn>
    <spawn count="1" respawn="90" respawn_random="0" period_of_day="none" group="assassing_kainak">
        <point x="15517" y="-114220" z="-243" h="13157"/>
        <npc id="19471"/>	<!--Таинственный Ассасин-->
    </spawn>
    <spawn count="1" respawn="90" respawn_random="0" period_of_day="none" group="assassing_kainak">
        <point x="15453" y="-114265" z="-246" h="25218"/>
        <npc id="19472"/>	<!--Таинственный Ассасин-->
    </spawn>
    <spawn count="1" respawn="90" respawn_random="0" period_of_day="none" group="assassing_kainak">
        <point x="15631" y="-114204" z="-239" h="7229"/>
        <npc id="19473"/>	<!--Таинственный Ассасин-->
    </spawn>
    <spawn count="1" respawn="90" respawn_random="0" period_of_day="none" group="assassing_kainak">
        <point x="16612" y="-115098" z="-252" h="13157"/>
        <npc id="19471"/>	<!--Таинственный Ассасин-->
    </spawn>
    <spawn count="1" respawn="90" respawn_random="0" period_of_day="none" group="assassing_kainak">
        <point x="16571" y="-115153" z="-248" h="25218"/>
        <npc id="19472"/>	<!--Таинственный Ассасин-->
    </spawn>
    <spawn count="1" respawn="90" respawn_random="0" period_of_day="none" group="assassing_kainak">
        <point x="16707" y="-115072" z="-254" h="7229"/>
        <npc id="19473"/>	<!--Таинственный Ассасин-->
    </spawn>
</list>
